.hgignore
.hgtags
ABOUT.txt
CHANGES.txt
COPYRIGHT.txt
LICENSE.txt
README.txt
base.cfg
setup.py
tl/__init__.py
tl.buildout_gtk.egg-info/PKG-INFO
tl.buildout_gtk.egg-info/SOURCES.txt
tl.buildout_gtk.egg-info/dependency_links.txt
tl.buildout_gtk.egg-info/entry_points.txt
tl.buildout_gtk.egg-info/namespace_packages.txt
tl.buildout_gtk.egg-info/not-zip-safe
tl.buildout_gtk.egg-info/requires.txt
tl.buildout_gtk.egg-info/top_level.txt
tl/buildout_gtk/__init__.py
tl/buildout_gtk/defaults.cfg
tl/buildout_gtk/recipe.py
tl/buildout_gtk/tests.py