Metadata-Version: 1.0
Name: tl.buildout-gtk
Version: 0.2.2
Summary: A zc.buildout recipe for installing pygtk, pyobject and pycairo.
Home-page: http://www.thomas-lotze.de/en/software/buildout-recipes/
Author: Thomas Lotze
Author-email: thomas@thomas-lotze.de
License: ZPL 2.1
Keywords: gtk gobject cairo pygtk pygobject pycairo buildout recipe
Platform: UNKNOWN
Classifier: Development Status :: 3 - Alpha
Classifier: Environment :: X11 Applications :: GTK
Classifier: Environment :: Plugins
Classifier: Framework :: Buildout
Classifier: Intended Audience :: Developers
Classifier: License :: OSI Approved :: Zope Public License
Classifier: Operating System :: OS Independent
Classifier: Programming Language :: Python
Classifier: Topic :: Software Development :: Build Tools
Classifier: Topic :: System :: Software Distribution
